custom_tree_view/CellTreeView.py
custom_tree_view/__init__.py
custom_tree_view/_imports_.py
custom_tree_view/async-CellTreeView.js
custom_tree_view/async-CellTreeView.js.map
custom_tree_view/custom_tree_view.min.js
custom_tree_view/custom_tree_view.min.js.map
custom_tree_view/metadata.json
custom_tree_view/package-info.json
custom_tree_view-1.0.0.dist-info/licenses/LICENSE
custom_tree_view-1.0.0.dist-info/METADATA
custom_tree_view-1.0.0.dist-info/WHEEL
custom_tree_view-1.0.0.dist-info/top_level.txt
custom_tree_view-1.0.0.dist-info/RECORD
