Metadata-Version: 2.4
Name: custom_tree_view
Version: 1.0.0
Summary: A custom TreeView component for hierarchically grouping celltypes
Author: Dennis Voelkl <dennis.voelkl@stud.uni-regensburg.de>
License: MIT
Classifier: Framework :: Dash
License-File: LICENSE
Dynamic: author
Dynamic: classifier
Dynamic: description
Dynamic: description-content-type
Dynamic: license
Dynamic: license-file
Dynamic: summary
